{
    "os": "Linux-5.4.0-166-generic-x86_64-with-glibc2.29",
    "python": "3.8.10",
    "heartbeatAt": "2023-11-22T18:37:46.402930",
    "startedAt": "2023-11-22T18:37:45.664963",
    "docker": null,
    "cuda": null,
    "args": [
        "learn",
        "puzzle",
        "mnist",
        "3",
        "3",
        "5000",
        "CubeSpaceAE_AMA4Conv",
        "kltune2",
        "--hash",
        "05-06T14:43:56.755GRID"
    ],
    "state": "running",
    "program": "./train_kltune.py",
    "codePathLocal": "train_kltune.py",
    "codePath": "train_kltune.py",
    "git": {
        "remote": "https://github.com/aymeric75/latplanClassicActionLoss.git",
        "commit": "46a29c6aaad742715c233e1973e59dd05bb17d34"
    },
    "email": "aymeric.barbin@hotmail.fr",
    "root": "/workspace/latplanRealOneHotActionsV2",
    "host": "71052289e0a2",
    "username": "root",
    "executable": "/usr/bin/python3",
    "cpu_count": 128,
    "cpu_count_logical": 256,
    "cpu_freq": {
        "current": 3388.3535781250002,
        "min": 1500.0,
        "max": 2250.0
    },
    "cpu_freq_per_core": [
        {
            "current": 3388.736,
            "min": 1500.0,
            "max": 2250.0
        },
        {
            "current": 3390.025,
            "min": 1500.0,
            "max": 2250.0
        },
        {
            "current": 3390.114,
            "min": 1500.0,
            "max": 2250.0
        },
        {
            "current": 3389.62,
            "min": 1500.0,
            "max": 2250.0
        },
        {
            "current": 3388.848,
            "min": 1500.0,
            "max": 2250.0
        },
        {
            "current": 3390.119,
            "min": 1500.0,
            "max": 2250.0
        },
        {
            "current": 3392.979,
            "min": 1500.0,
            "max": 2250.0
        },
        {
            "current": 3388.892,
            "min": 1500.0,
            "max": 2250.0
        },
        {
            "current": 3392.264,
            "min": 1500.0,
            "max": 2250.0
        },
        {
            "current": 3393.517,
            "min": 1500.0,
            "max": 2250.0
        },
        {
            "current": 3389.046,
            "min": 1500.0,
            "max": 2250.0
        },
        {
            "current": 3388.897,
            "min": 1500.0,
            "max": 2250.0
        },
        {
            "current": 3399.048,
            "min": 1500.0,
            "max": 2250.0
        },
        {
            "current": 3392.776,
            "min": 1500.0,
            "max": 2250.0
        },
        {
            "current": 3391.404,
            "min": 1500.0,
            "max": 2250.0
        },
        {
            "current": 3391.394,
            "min": 1500.0,
            "max": 2250.0
        },
        {
            "current": 3387.718,
            "min": 1500.0,
            "max": 2250.0
        },
        {
            "current": 3387.643,
            "min": 1500.0,
            "max": 2250.0
        },
        {
            "current": 3387.711,
            "min": 1500.0,
            "max": 2250.0
        },
        {
            "current": 3387.716,
            "min": 1500.0,
            "max": 2250.0
        },
        {
            "current": 3391.319,
            "min": 1500.0,
            "max": 2250.0
        },
        {
            "current": 3391.326,
            "min": 1500.0,
            "max": 2250.0
        },
        {
            "current": 3391.248,
            "min": 1500.0,
            "max": 2250.0
        },
        {
            "current": 3391.328,
            "min": 1500.0,
            "max": 2250.0
        },
        {
            "current": 3391.313,
            "min": 1500.0,
            "max": 2250.0
        },
        {
            "current": 3391.314,
            "min": 1500.0,
            "max": 2250.0
        },
        {
            "current": 3391.389,
            "min": 1500.0,
            "max": 2250.0
        },
        {
            "current": 3391.168,
            "min": 1500.0,
            "max": 2250.0
        },
        {
            "current": 3392.539,
            "min": 1500.0,
            "max": 2250.0
        },
        {
            "current": 3392.539,
            "min": 1500.0,
            "max": 2250.0
        },
        {
            "current": 3392.462,
            "min": 1500.0,
            "max": 2250.0
        },
        {
            "current": 3392.538,
            "min": 1500.0,
            "max": 2250.0
        },
        {
            "current": 3393.709,
            "min": 1500.0,
            "max": 2250.0
        },
        {
            "current": 3392.497,
            "min": 1500.0,
            "max": 2250.0
        },
        {
            "current": 3393.557,
            "min": 1500.0,
            "max": 2250.0
        },
        {
            "current": 3392.335,
            "min": 1500.0,
            "max": 2250.0
        },
        {
            "current": 3390.079,
            "min": 1500.0,
            "max": 2250.0
        },
        {
            "current": 3389.177,
            "min": 1500.0,
            "max": 2250.0
        },
        {
            "current": 3387.55,
            "min": 1500.0,
            "max": 2250.0
        },
        {
            "current": 3389.95,
            "min": 1500.0,
            "max": 2250.0
        },
        {
            "current": 3393.53,
            "min": 1500.0,
            "max": 2250.0
        },
        {
            "current": 3391.103,
            "min": 1500.0,
            "max": 2250.0
        },
        {
            "current": 3391.105,
            "min": 1500.0,
            "max": 2250.0
        },
        {
            "current": 3391.184,
            "min": 1500.0,
            "max": 2250.0
        },
        {
            "current": 3391.401,
            "min": 1500.0,
            "max": 2250.0
        },
        {
            "current": 3391.248,
            "min": 1500.0,
            "max": 2250.0
        },
        {
            "current": 3391.255,
            "min": 1500.0,
            "max": 2250.0
        },
        {
            "current": 3393.272,
            "min": 1500.0,
            "max": 2250.0
        },
        {
            "current": 3383.67,
            "min": 1500.0,
            "max": 2250.0
        },
        {
            "current": 3380.392,
            "min": 1500.0,
            "max": 2250.0
        },
        {
            "current": 3378.204,
            "min": 1500.0,
            "max": 2250.0
        },
        {
            "current": 3393.437,
            "min": 1500.0,
            "max": 2250.0
        },
        {
            "current": 3387.289,
            "min": 1500.0,
            "max": 2250.0
        },
        {
            "current": 3383.032,
            "min": 1500.0,
            "max": 2250.0
        },
        {
            "current": 3392.167,
            "min": 1500.0,
            "max": 2250.0
        },
        {
            "current": 3383.74,
            "min": 1500.0,
            "max": 2250.0
        },
        {
            "current": 3393.086,
            "min": 1500.0,
            "max": 2250.0
        },
        {
            "current": 3391.087,
            "min": 1500.0,
            "max": 2250.0
        },
        {
            "current": 3391.361,
            "min": 1500.0,
            "max": 2250.0
        },
        {
            "current": 3391.036,
            "min": 1500.0,
            "max": 2250.0
        },
        {
            "current": 3391.334,
            "min": 1500.0,
            "max": 2250.0
        },
        {
            "current": 3391.945,
            "min": 1500.0,
            "max": 2250.0
        },
        {
            "current": 3389.884,
            "min": 1500.0,
            "max": 2250.0
        },
        {
            "current": 3389.635,
            "min": 1500.0,
            "max": 2250.0
        },
        {
            "current": 3389.926,
            "min": 1500.0,
            "max": 2250.0
        },
        {
            "current": 3389.994,
            "min": 1500.0,
            "max": 2250.0
        },
        {
            "current": 3390.237,
            "min": 1500.0,
            "max": 2250.0
        },
        {
            "current": 3390.052,
            "min": 1500.0,
            "max": 2250.0
        },
        {
            "current": 3391.398,
            "min": 1500.0,
            "max": 2250.0
        },
        {
            "current": 3391.364,
            "min": 1500.0,
            "max": 2250.0
        },
        {
            "current": 3391.123,
            "min": 1500.0,
            "max": 2250.0
        },
        {
            "current": 3391.233,
            "min": 1500.0,
            "max": 2250.0
        },
        {
            "current": 3393.729,
            "min": 1500.0,
            "max": 2250.0
        },
        {
            "current": 3393.465,
            "min": 1500.0,
            "max": 2250.0
        },
        {
            "current": 3393.486,
            "min": 1500.0,
            "max": 2250.0
        },
        {
            "current": 3393.658,
            "min": 1500.0,
            "max": 2250.0
        },
        {
            "current": 3391.343,
            "min": 1500.0,
            "max": 2250.0
        },
        {
            "current": 3391.333,
            "min": 1500.0,
            "max": 2250.0
        },
        {
            "current": 3391.007,
            "min": 1500.0,
            "max": 2250.0
        },
        {
            "current": 3391.233,
            "min": 1500.0,
            "max": 2250.0
        },
        {
            "current": 3391.33,
            "min": 1500.0,
            "max": 2250.0
        },
        {
            "current": 3391.36,
            "min": 1500.0,
            "max": 2250.0
        },
        {
            "current": 3391.225,
            "min": 1500.0,
            "max": 2250.0
        },
        {
            "current": 3391.254,
            "min": 1500.0,
            "max": 2250.0
        },
        {
            "current": 3392.527,
            "min": 1500.0,
            "max": 2250.0
        },
        {
            "current": 3392.296,
            "min": 1500.0,
            "max": 2250.0
        },
        {
            "current": 3392.524,
            "min": 1500.0,
            "max": 2250.0
        },
        {
            "current": 3392.522,
            "min": 1500.0,
            "max": 2250.0
        },
        {
            "current": 3393.542,
            "min": 1500.0,
            "max": 2250.0
        },
        {
            "current": 3393.626,
            "min": 1500.0,
            "max": 2250.0
        },
        {
            "current": 3393.522,
            "min": 1500.0,
            "max": 2250.0
        },
        {
            "current": 3393.452,
            "min": 1500.0,
            "max": 2250.0
        },
        {
            "current": 3389.923,
            "min": 1500.0,
            "max": 2250.0
        },
        {
            "current": 3389.802,
            "min": 1500.0,
            "max": 2250.0
        },
        {
            "current": 3389.811,
            "min": 1500.0,
            "max": 2250.0
        },
        {
            "current": 3389.982,
            "min": 1500.0,
            "max": 2250.0
        },
        {
            "current": 3393.341,
            "min": 1500.0,
            "max": 2250.0
        },
        {
            "current": 3377.657,
            "min": 1500.0,
            "max": 2250.0
        },
        {
            "current": 3391.387,
            "min": 1500.0,
            "max": 2250.0
        },
        {
            "current": 3391.398,
            "min": 1500.0,
            "max": 2250.0
        },
        {
            "current": 3393.493,
            "min": 1500.0,
            "max": 2250.0
        },
        {
            "current": 3393.57,
            "min": 1500.0,
            "max": 2250.0
        },
        {
            "current": 3393.614,
            "min": 1500.0,
            "max": 2250.0
        },
        {
            "current": 3393.514,
            "min": 1500.0,
            "max": 2250.0
        },
        {
            "current": 3391.259,
            "min": 1500.0,
            "max": 2250.0
        },
        {
            "current": 3391.257,
            "min": 1500.0,
            "max": 2250.0
        },
        {
            "current": 3395.61,
            "min": 1500.0,
            "max": 2250.0
        },
        {
            "current": 3391.311,
            "min": 1500.0,
            "max": 2250.0
        },
        {
            "current": 3388.61,
            "min": 1500.0,
            "max": 2250.0
        },
        {
            "current": 3388.866,
            "min": 1500.0,
            "max": 2250.0
        },
        {
            "current": 3389.059,
            "min": 1500.0,
            "max": 2250.0
        },
        {
            "current": 3388.913,
            "min": 1500.0,
            "max": 2250.0
        },
        {
            "current": 3285.845,
            "min": 1500.0,
            "max": 2250.0
        },
        {
            "current": 3389.674,
            "min": 1500.0,
            "max": 2250.0
        },
        {
            "current": 3390.016,
            "min": 1500.0,
            "max": 2250.0
        },
        {
            "current": 3281.511,
            "min": 1500.0,
            "max": 2250.0
        },
        {
            "current": 3279.889,
            "min": 1500.0,
            "max": 2250.0
        },
        {
            "current": 3290.635,
            "min": 1500.0,
            "max": 2250.0
        },
        {
            "current": 3391.376,
            "min": 1500.0,
            "max": 2250.0
        },
        {
            "current": 3281.077,
            "min": 1500.0,
            "max": 2250.0
        },
        {
            "current": 3291.149,
            "min": 1500.0,
            "max": 2250.0
        },
        {
            "current": 3285.009,
            "min": 1500.0,
            "max": 2250.0
        },
        {
            "current": 3389.826,
            "min": 1500.0,
            "max": 2250.0
        },
        {
            "current": 3390.219,
            "min": 1500.0,
            "max": 2250.0
        },
        {
            "current": 3273.253,
            "min": 1500.0,
            "max": 2250.0
        },
        {
            "current": 3387.431,
            "min": 1500.0,
            "max": 2250.0
        },
        {
            "current": 3387.295,
            "min": 1500.0,
            "max": 2250.0
        },
        {
            "current": 3388.85,
            "min": 1500.0,
            "max": 2250.0
        },
        {
            "current": 3388.212,
            "min": 1500.0,
            "max": 2250.0
        },
        {
            "current": 3390.08,
            "min": 1500.0,
            "max": 2250.0
        },
        {
            "current": 3390.168,
            "min": 1500.0,
            "max": 2250.0
        },
        {
            "current": 3387.878,
            "min": 1500.0,
            "max": 2250.0
        },
        {
            "current": 3388.919,
            "min": 1500.0,
            "max": 2250.0
        },
        {
            "current": 3389.016,
            "min": 1500.0,
            "max": 2250.0
        },
        {
            "current": 3388.921,
            "min": 1500.0,
            "max": 2250.0
        },
        {
            "current": 3388.958,
            "min": 1500.0,
            "max": 2250.0
        },
        {
            "current": 3389.042,
            "min": 1500.0,
            "max": 2250.0
        },
        {
            "current": 3388.806,
            "min": 1500.0,
            "max": 2250.0
        },
        {
            "current": 3389.094,
            "min": 1500.0,
            "max": 2250.0
        },
        {
            "current": 3388.945,
            "min": 1500.0,
            "max": 2250.0
        },
        {
            "current": 3391.183,
            "min": 1500.0,
            "max": 2250.0
        },
        {
            "current": 3391.422,
            "min": 1500.0,
            "max": 2250.0
        },
        {
            "current": 3391.425,
            "min": 1500.0,
            "max": 2250.0
        },
        {
            "current": 3391.416,
            "min": 1500.0,
            "max": 2250.0
        },
        {
            "current": 3387.775,
            "min": 1500.0,
            "max": 2250.0
        },
        {
            "current": 3387.7,
            "min": 1500.0,
            "max": 2250.0
        },
        {
            "current": 3387.77,
            "min": 1500.0,
            "max": 2250.0
        },
        {
            "current": 3387.775,
            "min": 1500.0,
            "max": 2250.0
        },
        {
            "current": 3391.339,
            "min": 1500.0,
            "max": 2250.0
        },
        {
            "current": 3391.349,
            "min": 1500.0,
            "max": 2250.0
        },
        {
            "current": 3391.273,
            "min": 1500.0,
            "max": 2250.0
        },
        {
            "current": 3391.351,
            "min": 1500.0,
            "max": 2250.0
        },
        {
            "current": 3391.337,
            "min": 1500.0,
            "max": 2250.0
        },
        {
            "current": 3391.337,
            "min": 1500.0,
            "max": 2250.0
        },
        {
            "current": 3391.408,
            "min": 1500.0,
            "max": 2250.0
        },
        {
            "current": 3391.192,
            "min": 1500.0,
            "max": 2250.0
        },
        {
            "current": 3392.548,
            "min": 1500.0,
            "max": 2250.0
        },
        {
            "current": 3392.548,
            "min": 1500.0,
            "max": 2250.0
        },
        {
            "current": 3392.476,
            "min": 1500.0,
            "max": 2250.0
        },
        {
            "current": 3392.546,
            "min": 1500.0,
            "max": 2250.0
        },
        {
            "current": 3393.427,
            "min": 1500.0,
            "max": 2250.0
        },
        {
            "current": 3393.537,
            "min": 1500.0,
            "max": 2250.0
        },
        {
            "current": 3391.136,
            "min": 1500.0,
            "max": 2250.0
        },
        {
            "current": 3393.708,
            "min": 1500.0,
            "max": 2250.0
        },
        {
            "current": 3391.374,
            "min": 1500.0,
            "max": 2250.0
        },
        {
            "current": 3390.778,
            "min": 1500.0,
            "max": 2250.0
        },
        {
            "current": 3389.849,
            "min": 1500.0,
            "max": 2250.0
        },
        {
            "current": 3390.722,
            "min": 1500.0,
            "max": 2250.0
        },
        {
            "current": 3391.276,
            "min": 1500.0,
            "max": 2250.0
        },
        {
            "current": 3393.401,
            "min": 1500.0,
            "max": 2250.0
        },
        {
            "current": 3393.552,
            "min": 1500.0,
            "max": 2250.0
        },
        {
            "current": 3351.997,
            "min": 1500.0,
            "max": 2250.0
        },
        {
            "current": 3393.221,
            "min": 1500.0,
            "max": 2250.0
        },
        {
            "current": 3393.531,
            "min": 1500.0,
            "max": 2250.0
        },
        {
            "current": 3388.437,
            "min": 1500.0,
            "max": 2250.0
        },
        {
            "current": 3391.35,
            "min": 1500.0,
            "max": 2250.0
        },
        {
            "current": 3386.606,
            "min": 1500.0,
            "max": 2250.0
        },
        {
            "current": 3377.717,
            "min": 1500.0,
            "max": 2250.0
        },
        {
            "current": 3377.773,
            "min": 1500.0,
            "max": 2250.0
        },
        {
            "current": 3387.693,
            "min": 1500.0,
            "max": 2250.0
        },
        {
            "current": 3388.609,
            "min": 1500.0,
            "max": 2250.0
        },
        {
            "current": 3322.818,
            "min": 1500.0,
            "max": 2250.0
        },
        {
            "current": 3380.668,
            "min": 1500.0,
            "max": 2250.0
        },
        {
            "current": 3381.049,
            "min": 1500.0,
            "max": 2250.0
        },
        {
            "current": 3389.311,
            "min": 1500.0,
            "max": 2250.0
        },
        {
            "current": 3393.666,
            "min": 1500.0,
            "max": 2250.0
        },
        {
            "current": 3391.658,
            "min": 1500.0,
            "max": 2250.0
        },
        {
            "current": 3397.679,
            "min": 1500.0,
            "max": 2250.0
        },
        {
            "current": 3392.906,
            "min": 1500.0,
            "max": 2250.0
        },
        {
            "current": 3392.323,
            "min": 1500.0,
            "max": 2250.0
        },
        {
            "current": 3392.293,
            "min": 1500.0,
            "max": 2250.0
        },
        {
            "current": 3383.247,
            "min": 1500.0,
            "max": 2250.0
        },
        {
            "current": 3389.962,
            "min": 1500.0,
            "max": 2250.0
        },
        {
            "current": 3390.026,
            "min": 1500.0,
            "max": 2250.0
        },
        {
            "current": 3390.269,
            "min": 1500.0,
            "max": 2250.0
        },
        {
            "current": 3390.083,
            "min": 1500.0,
            "max": 2250.0
        },
        {
            "current": 3391.381,
            "min": 1500.0,
            "max": 2250.0
        },
        {
            "current": 3391.386,
            "min": 1500.0,
            "max": 2250.0
        },
        {
            "current": 3391.159,
            "min": 1500.0,
            "max": 2250.0
        },
        {
            "current": 3391.151,
            "min": 1500.0,
            "max": 2250.0
        },
        {
            "current": 3393.729,
            "min": 1500.0,
            "max": 2250.0
        },
        {
            "current": 3393.461,
            "min": 1500.0,
            "max": 2250.0
        },
        {
            "current": 3393.495,
            "min": 1500.0,
            "max": 2250.0
        },
        {
            "current": 3393.659,
            "min": 1500.0,
            "max": 2250.0
        },
        {
            "current": 3391.367,
            "min": 1500.0,
            "max": 2250.0
        },
        {
            "current": 3391.289,
            "min": 1500.0,
            "max": 2250.0
        },
        {
            "current": 3391.044,
            "min": 1500.0,
            "max": 2250.0
        },
        {
            "current": 3391.252,
            "min": 1500.0,
            "max": 2250.0
        },
        {
            "current": 3391.353,
            "min": 1500.0,
            "max": 2250.0
        },
        {
            "current": 3391.39,
            "min": 1500.0,
            "max": 2250.0
        },
        {
            "current": 3392.135,
            "min": 1500.0,
            "max": 2250.0
        },
        {
            "current": 3391.274,
            "min": 1500.0,
            "max": 2250.0
        },
        {
            "current": 3392.539,
            "min": 1500.0,
            "max": 2250.0
        },
        {
            "current": 3392.306,
            "min": 1500.0,
            "max": 2250.0
        },
        {
            "current": 3392.532,
            "min": 1500.0,
            "max": 2250.0
        },
        {
            "current": 3392.533,
            "min": 1500.0,
            "max": 2250.0
        },
        {
            "current": 3393.546,
            "min": 1500.0,
            "max": 2250.0
        },
        {
            "current": 3393.63,
            "min": 1500.0,
            "max": 2250.0
        },
        {
            "current": 3393.621,
            "min": 1500.0,
            "max": 2250.0
        },
        {
            "current": 3393.452,
            "min": 1500.0,
            "max": 2250.0
        },
        {
            "current": 3389.954,
            "min": 1500.0,
            "max": 2250.0
        },
        {
            "current": 3389.835,
            "min": 1500.0,
            "max": 2250.0
        },
        {
            "current": 3389.911,
            "min": 1500.0,
            "max": 2250.0
        },
        {
            "current": 3390.009,
            "min": 1500.0,
            "max": 2250.0
        },
        {
            "current": 3391.15,
            "min": 1500.0,
            "max": 2250.0
        },
        {
            "current": 3391.132,
            "min": 1500.0,
            "max": 2250.0
        },
        {
            "current": 3391.409,
            "min": 1500.0,
            "max": 2250.0
        },
        {
            "current": 3391.419,
            "min": 1500.0,
            "max": 2250.0
        },
        {
            "current": 3393.498,
            "min": 1500.0,
            "max": 2250.0
        },
        {
            "current": 3393.58,
            "min": 1500.0,
            "max": 2250.0
        },
        {
            "current": 3393.618,
            "min": 1500.0,
            "max": 2250.0
        },
        {
            "current": 3393.516,
            "min": 1500.0,
            "max": 2250.0
        },
        {
            "current": 3391.279,
            "min": 1500.0,
            "max": 2250.0
        },
        {
            "current": 3391.276,
            "min": 1500.0,
            "max": 2250.0
        },
        {
            "current": 3391.361,
            "min": 1500.0,
            "max": 2250.0
        },
        {
            "current": 3391.324,
            "min": 1500.0,
            "max": 2250.0
        },
        {
            "current": 3388.653,
            "min": 1500.0,
            "max": 2250.0
        },
        {
            "current": 3388.906,
            "min": 1500.0,
            "max": 2250.0
        },
        {
            "current": 3389.098,
            "min": 1500.0,
            "max": 2250.0
        },
        {
            "current": 3388.949,
            "min": 1500.0,
            "max": 2250.0
        },
        {
            "current": 3283.375,
            "min": 1500.0,
            "max": 2250.0
        },
        {
            "current": 3389.694,
            "min": 1500.0,
            "max": 2250.0
        },
        {
            "current": 3390.048,
            "min": 1500.0,
            "max": 2250.0
        },
        {
            "current": 3287.713,
            "min": 1500.0,
            "max": 2250.0
        },
        {
            "current": 3281.112,
            "min": 1500.0,
            "max": 2250.0
        },
        {
            "current": 3291.603,
            "min": 1500.0,
            "max": 2250.0
        },
        {
            "current": 3391.341,
            "min": 1500.0,
            "max": 2250.0
        },
        {
            "current": 3282.235,
            "min": 1500.0,
            "max": 2250.0
        },
        {
            "current": 3292.633,
            "min": 1500.0,
            "max": 2250.0
        },
        {
            "current": 3288.367,
            "min": 1500.0,
            "max": 2250.0
        },
        {
            "current": 3389.637,
            "min": 1500.0,
            "max": 2250.0
        },
        {
            "current": 3389.916,
            "min": 1500.0,
            "max": 2250.0
        },
        {
            "current": 3274.421,
            "min": 1500.0,
            "max": 2250.0
        },
        {
            "current": 3388.82,
            "min": 1500.0,
            "max": 2250.0
        },
        {
            "current": 3387.385,
            "min": 1500.0,
            "max": 2250.0
        },
        {
            "current": 3387.562,
            "min": 1500.0,
            "max": 2250.0
        }
    ],
    "disk": {
        "/": {
            "total": 1757.7545127868652,
            "used": 1068.3251457214355
        }
    },
    "gpu": "NVIDIA A100-SXM4-80GB",
    "gpu_count": 1,
    "memory": {
        "total": 2015.6730728149414
    }
}
