{
  "image_filename": "init.png",
  "relationships": {
    "behind": [
      [],
      [],
      [],
      []
    ],
    "right": [
      [
        1
      ],
      [],
      [
        1
      ],
      [
        0,
        1,
        2
      ]
    ],
    "front": [
      [],
      [],
      [],
      []
    ],
    "left": [
      [
        3
      ],
      [
        0,
        2,
        3
      ],
      [
        3
      ],
      []
    ]
  },
  "objects": [
    {
      "size": 0.7,
      "color": [
        0.0,
        1.0,
        0.0,
        1.0
      ],
      "pixel_coords": [
        92,
        72,
        16.702682495117188
      ],
      "shape": "SmoothCylinder",
      "bbox": [
        85.0,
        64.0,
        100.0,
        81.0
      ],
      "rotation": 96.69313199879525,
      "material": "Rubber",
      "id": 0,
      "location": [
        1.75,
        0,
        0.7
      ],
      "stackable": true
    },
    {
      "size": 0.7,
      "color": [
        0.0,
        0.0,
        0.0,
        1.0
      ],
      "pixel_coords": [
        109,
        72,
        16.702682495117188
      ],
      "shape": "SmoothCylinder",
      "bbox": [
        101.0,
        64.0,
        118.0,
        81.0
      ],
      "rotation": 59.689306760869776,
      "material": "Rubber",
      "id": 1,
      "location": [
        3.5,
        0,
        0.7
      ],
      "stackable": true
    },
    {
      "size": 0.7,
      "color": [
        1.0,
        0.0,
        0.0,
        1.0
      ],
      "pixel_coords": [
        92,
        59,
        16.444677352905273
      ],
      "shape": "SmoothCylinder",
      "bbox": [
        85.0,
        51.0,
        101.0,
        68.0
      ],
      "rotation": 139.93556854723101,
      "material": "Rubber",
      "id": 2,
      "location": [
        1.75,
        0,
        2.0999999999999996
      ],
      "stackable": true
    },
    {
      "size": 0.7,
      "color": [
        0.0,
        0.0,
        1.0,
        1.0
      ],
      "pixel_coords": [
        75,
        72,
        16.702682495117188
      ],
      "shape": "SmoothCylinder",
      "bbox": [
        68.0,
        64.0,
        82.0,
        81.0
      ],
      "rotation": 237.7549663722691,
      "material": "Rubber",
      "id": 3,
      "location": [
        0.0,
        0,
        0.7
      ],
      "stackable": true
    }
  ],
  "directions": {
    "behind": [
      0.0,
      0.9999999403953552,
      0.0
    ],
    "above": [
      0.0,
      0.0,
      0.9999999403953552
    ],
    "right": [
      1.0,
      -0.0,
      -0.0
    ],
    "front": [
      -0.0,
      -0.9999999403953552,
      -0.0
    ],
    "left": [
      -1.0,
      0.0,
      0.0
    ],
    "below": [
      -0.0,
      -0.0,
      -0.9999999403953552
    ]
  }
}